{
  "journeyHeroMetrics": [
    { "label": "Total Enrollment", "value": "361.5K", "iconKey": "Users", "sub": "+3.2% YoY" },
    { "label": "System Avg Score", "value": "74", "iconKey": "BookOpen", "sub": "Target: 85" },
    { "label": "Overall Completion", "value": "88%", "iconKey": "GraduationCap", "sub": "Target: 95%" },
    { "label": "Critical Drop-offs", "value": "2", "iconKey": "AlertTriangle", "sub": "Middle → Higher" }
  ],
  "journeyStages": [
    {
      "id": "kg",
      "label": "Kindergarten",
      "shortLabel": "KG",
      "ageRange": "4–5 yrs",
      "enrollment": 42500,
      "completionRate": 98,
      "avgScore": 82,
      "status": "green",
      "keyMetrics": [
        { "label": "Readiness Score", "value": "82%", "trend": "up" },
        { "label": "Attendance", "value": "94%", "trend": "flat" },
        { "label": "Social-Emotional", "value": "78%", "trend": "up" }
      ]
    },
    {
      "id": "primary",
      "label": "Primary School",
      "shortLabel": "Primary",
      "ageRange": "6–11 yrs",
      "enrollment": 128000,
      "completionRate": 96,
      "avgScore": 74,
      "status": "amber",
      "keyMetrics": [
        { "label": "Literacy Rate", "value": "72%", "trend": "up" },
        { "label": "Numeracy Rate", "value": "68%", "trend": "flat" },
        { "label": "STEM Interest", "value": "61%", "trend": "up" }
      ]
    },
    {
      "id": "middle",
      "label": "Middle School",
      "shortLabel": "Middle",
      "ageRange": "12–14 yrs",
      "enrollment": 89000,
      "completionRate": 91,
      "avgScore": 68,
      "status": "amber",
      "keyMetrics": [
        { "label": "Core Subjects", "value": "68%", "trend": "flat" },
        { "label": "Critical Thinking", "value": "55%", "trend": "up" },
        { "label": "Engagement", "value": "62%", "trend": "down" }
      ]
    },
    {
      "id": "secondary",
      "label": "Secondary School",
      "shortLabel": "Secondary",
      "ageRange": "15–17 yrs",
      "enrollment": 64000,
      "completionRate": 84,
      "avgScore": 65,
      "status": "red",
      "keyMetrics": [
        { "label": "Graduation Rate", "value": "84%", "trend": "up" },
        { "label": "University Ready", "value": "58%", "trend": "flat" },
        { "label": "Career Pathway", "value": "45%", "trend": "up" }
      ]
    },
    {
      "id": "higher",
      "label": "Higher Education",
      "shortLabel": "Higher Ed",
      "ageRange": "18–22 yrs",
      "enrollment": 38000,
      "completionRate": 72,
      "avgScore": 71,
      "status": "red",
      "keyMetrics": [
        { "label": "Completion Rate", "value": "72%", "trend": "flat" },
        { "label": "Employment Rate", "value": "68%", "trend": "up" },
        { "label": "Research Output", "value": "42%", "trend": "up" }
      ]
    }
  ],
  "transitions": [
    { "from": "kg", "to": "primary", "rate": 97, "dropoff": 3, "status": "green", "riskFactors": ["Language barriers", "Late enrollment"] },
    { "from": "primary", "to": "middle", "rate": 93, "dropoff": 7, "status": "amber", "riskFactors": ["Learning gaps in math", "Social adjustment", "Family relocation"] },
    { "from": "middle", "to": "secondary", "rate": 86, "dropoff": 14, "status": "red", "riskFactors": ["Academic disengagement", "Curriculum difficulty spike", "Mental health"] },
    { "from": "secondary", "to": "higher", "rate": 71, "dropoff": 29, "status": "red", "riskFactors": ["University readiness gaps", "Financial constraints", "Vocational preference"] }
  ],
  "cohortTrends": [
    { "year": "2021", "kg": 40200, "primary": 122000, "middle": 85000, "secondary": 61000, "higher": 34000 },
    { "year": "2022", "kg": 41000, "primary": 124000, "middle": 86500, "secondary": 62000, "higher": 35500 },
    { "year": "2023", "kg": 41500, "primary": 125500, "middle": 87500, "secondary": 62800, "higher": 36200 },
    { "year": "2024", "kg": 42000, "primary": 126800, "middle": 88200, "secondary": 63200, "higher": 37000 },
    { "year": "2025", "kg": 42200, "primary": 127500, "middle": 88800, "secondary": 63800, "higher": 37500 },
    { "year": "2026", "kg": 42500, "primary": 128000, "middle": 89000, "secondary": 64000, "higher": 38000 }
  ],
  "riskMatrix": [
    { "stage": "KG", "dimension": "Attendance", "value": 94, "status": "green" },
    { "stage": "KG", "dimension": "Learning", "value": 82, "status": "green" },
    { "stage": "KG", "dimension": "Wellbeing", "value": 78, "status": "amber" },
    { "stage": "KG", "dimension": "Equity", "value": 85, "status": "green" },
    { "stage": "Primary", "dimension": "Attendance", "value": 91, "status": "green" },
    { "stage": "Primary", "dimension": "Learning", "value": 72, "status": "amber" },
    { "stage": "Primary", "dimension": "Wellbeing", "value": 75, "status": "amber" },
    { "stage": "Primary", "dimension": "Equity", "value": 70, "status": "amber" },
    { "stage": "Middle", "dimension": "Attendance", "value": 87, "status": "amber" },
    { "stage": "Middle", "dimension": "Learning", "value": 68, "status": "amber" },
    { "stage": "Middle", "dimension": "Wellbeing", "value": 62, "status": "red" },
    { "stage": "Middle", "dimension": "Equity", "value": 65, "status": "red" },
    { "stage": "Secondary", "dimension": "Attendance", "value": 82, "status": "amber" },
    { "stage": "Secondary", "dimension": "Learning", "value": 65, "status": "red" },
    { "stage": "Secondary", "dimension": "Wellbeing", "value": 58, "status": "red" },
    { "stage": "Secondary", "dimension": "Equity", "value": 60, "status": "red" },
    { "stage": "Higher Ed", "dimension": "Attendance", "value": 78, "status": "amber" },
    { "stage": "Higher Ed", "dimension": "Learning", "value": 71, "status": "amber" },
    { "stage": "Higher Ed", "dimension": "Wellbeing", "value": 65, "status": "red" },
    { "stage": "Higher Ed", "dimension": "Equity", "value": 55, "status": "red" }
  ]
}
